rhosocial/activerecord/model.py
rhosocial/activerecord/backend/__init__.py
rhosocial/activerecord/backend/base.py
rhosocial/activerecord/backend/basic_type_converter.py
rhosocial/activerecord/backend/capabilities.py
rhosocial/activerecord/backend/config.py
rhosocial/activerecord/backend/dialect.py
rhosocial/activerecord/backend/errors.py
rhosocial/activerecord/backend/helpers.py
rhosocial/activerecord/backend/transaction.py
rhosocial/activerecord/backend/type_converters.py
rhosocial/activerecord/backend/typing.py
rhosocial/activerecord/backend/impl/__init__.py
rhosocial/activerecord/backend/impl/sqlite/__init__.py
rhosocial/activerecord/backend/impl/sqlite/backend.py
rhosocial/activerecord/backend/impl/sqlite/config.py
rhosocial/activerecord/backend/impl/sqlite/dialect.py
rhosocial/activerecord/backend/impl/sqlite/transaction.py
rhosocial/activerecord/backend/impl/sqlite/type_converters.py
rhosocial/activerecord/backend/impl/sqlite/types.py
rhosocial/activerecord/base/__init__.py
rhosocial/activerecord/base/base.py
rhosocial/activerecord/base/query_mixin.py
rhosocial/activerecord/base/typing.py
rhosocial/activerecord/field/__init__.py
rhosocial/activerecord/field/integer_pk.py
rhosocial/activerecord/field/soft_delete.py
rhosocial/activerecord/field/timestamp.py
rhosocial/activerecord/field/uuid.py
rhosocial/activerecord/field/version.py
rhosocial/activerecord/interface/__init__.py
rhosocial/activerecord/interface/base.py
rhosocial/activerecord/interface/model.py
rhosocial/activerecord/interface/query.py
rhosocial/activerecord/interface/update.py
rhosocial/activerecord/query/__init__.py
rhosocial/activerecord/query/active_query.py
rhosocial/activerecord/query/aggregate.py
rhosocial/activerecord/query/base.py
rhosocial/activerecord/query/cte.py
rhosocial/activerecord/query/dict_query.py
rhosocial/activerecord/query/expression.py
rhosocial/activerecord/query/join.py
rhosocial/activerecord/query/range.py
rhosocial/activerecord/query/relational.py
rhosocial_activerecord-1.0.0.dev12.dist-info/licenses/LICENSE
rhosocial_activerecord-1.0.0.dev12.dist-info/METADATA
rhosocial_activerecord-1.0.0.dev12.dist-info/WHEEL
rhosocial_activerecord-1.0.0.dev12.dist-info/top_level.txt
rhosocial_activerecord-1.0.0.dev12.dist-info/RECORD
