Metadata-Version: 2.4
Name: rhosocial_activerecord
Version: 1.0.0.dev12
Summary: A modern, Pythonic implementation of the ActiveRecord pattern, providing an elegant and intuitive interface for database operations with type safety and rich features.
Author-email: vistart <i@vistart.me>
License:                                  Apache License
Project-URL: Homepage, https://github.com/rhosocial/python-activerecord
Project-URL: Documentation, https://docs.python-activerecord.dev.rho.social/
Project-URL: Repository, https://github.com/rhosocial/python-activerecord.git
Project-URL: Issues, https://github.com/rhosocial/python-activerecord/issues
Keywords: activerecord,orm,database,pydantic,relation
Classifier: Development Status :: 3 - Alpha
Classifier: Intended Audience :: Developers
Classifier: License :: OSI Approved :: Apache Software License
Classifier: Programming Language :: Python :: 3
Classifier: Programming Language :: Python :: 3.8
Classifier: Programming Language :: Python :: 3.9
Classifier: Programming Language :: Python :: 3.10
Classifier: Programming Language :: Python :: 3.11
Classifier: Programming Language :: Python :: 3.12
Classifier: Programming Language :: Python :: 3.13
Classifier: Programming Language :: Python :: 3.14
Classifier: Programming Language :: Python :: 3 :: Only
Classifier: Framework :: Pydantic
Classifier: Framework :: Pydantic :: 2
Classifier: Intended Audience :: Developers
Classifier: Topic :: Database
Classifier: Topic :: Software Development :: Libraries
Classifier: Topic :: Software Development :: Libraries :: Python Modules
Requires-Python: >=3.8
License-File: LICENSE
Requires-Dist: pydantic==2.10.6; python_version == "3.8"
Requires-Dist: pydantic-core==2.27.2; python_version == "3.8"
Requires-Dist: pydantic>=2.12.0; python_version >= "3.9"
Requires-Dist: pydantic-core>=2.41.0; python_version >= "3.9"
Requires-Dist: typing-extensions>=4.12.0
Requires-Dist: pytz>=2025.2
Requires-Dist: python-dateutil>=2.9.0
Requires-Dist: tzlocal>=5.2
Requires-Dist: backports.zoneinfo>=0.2.1; python_version < "3.9"
Provides-Extra: mysql
Requires-Dist: rhosocial-activerecord-mysql<2.0.0,>=1.0.0; extra == "mysql"
Provides-Extra: mariadb
Requires-Dist: rhosocial-activerecord-mariadb<2.0.0,>=1.0.0; extra == "mariadb"
Provides-Extra: pgsql
Requires-Dist: rhosocial-activerecord-pgsql<2.0.0,>=1.0.0; extra == "pgsql"
Provides-Extra: oracle
Requires-Dist: rhosocial-activerecord-oracle<2.0.0,>=1.0.0; extra == "oracle"
Provides-Extra: mssql
Requires-Dist: rhosocial-activerecord-mssql<2.0.0,>=1.0.0; extra == "mssql"
Provides-Extra: databases
Requires-Dist: rhosocial-activerecord-mysql<2.0.0,>=1.0.0; extra == "databases"
Requires-Dist: rhosocial-activerecord-mariadb<2.0.0,>=1.0.0; extra == "databases"
Requires-Dist: rhosocial-activerecord-pgsql<2.0.0,>=1.0.0; extra == "databases"
Requires-Dist: rhosocial-activerecord-oracle<2.0.0,>=1.0.0; extra == "databases"
Requires-Dist: rhosocial-activerecord-mssql<2.0.0,>=1.0.0; extra == "databases"
Provides-Extra: migration
Requires-Dist: rhosocial-activerecord-migration<2.0.0,>=1.0.0; extra == "migration"
Provides-Extra: all
Requires-Dist: rhosocial-activerecord-mysql<2.0.0,>=1.0.0; extra == "all"
Requires-Dist: rhosocial-activerecord-mariadb<2.0.0,>=1.0.0; extra == "all"
Requires-Dist: rhosocial-activerecord-pgsql<2.0.0,>=1.0.0; extra == "all"
Requires-Dist: rhosocial-activerecord-oracle<2.0.0,>=1.0.0; extra == "all"
Requires-Dist: rhosocial-activerecord-mssql<2.0.0,>=1.0.0; extra == "all"
Requires-Dist: rhosocial-activerecord-migration<2.0.0,>=1.0.0; extra == "all"
Provides-Extra: test
Requires-Dist: pytest>=7.0.0; extra == "test"
Requires-Dist: coverage>=7.0.0; extra == "test"
Requires-Dist: pytest-asyncio>=0.21.0; extra == "test"
Requires-Dist: aiosqlite>=0.19.0; extra == "test"
Requires-Dist: aiofiles>=23.0.0; extra == "test"
Requires-Dist: pytest-cov>=4.0.0; extra == "test"
Requires-Dist: pytest-xdist>=3.6.1; extra == "test"
Requires-Dist: pytest-timeout>=2.1.0; extra == "test"
Requires-Dist: pytest-rerunfailures>=15.0; extra == "test"
Requires-Dist: pydantic[email]; extra == "test"
Requires-Dist: pyyaml>=6.0.2; extra == "test"
Provides-Extra: dev
Requires-Dist: black>=23.0.0; extra == "dev"
Requires-Dist: isort>=5.0.0; extra == "dev"
Requires-Dist: mypy>=1.0.0; extra == "dev"
Requires-Dist: ruff>=0.1.0; extra == "dev"
Requires-Dist: pre-commit>=3.0.0; extra == "dev"
Provides-Extra: docs
Requires-Dist: sphinx>=7.0.0; extra == "docs"
Requires-Dist: sphinx-rtd-theme>=1.0.0; extra == "docs"
Requires-Dist: myst-parser>=2.0.0; extra == "docs"
Dynamic: license-file
